Metadata-Version: 2.1
Name: xnatio
Version: 0.0.1
Summary: A library for gathering data from the XNAT database
Home-page: https://github.com/AidanKelley/xnatio
Author: Aidan Kelley
Author-email: aidankelley@wustl.edu
License: XNAT
Platform: UNKNOWN
